bomshell/__init__.py
bomshell/__main__.py
bomshell/bom_paths.py
bomshell/catalog.json
bomshell/cli.py
bomshell/dump_gis.py
bomshell/fetch.py
bomshell/fetch_gis.py
bomshell/knobs.py
bomshell/settings.py
bomshell-1.1.0.dist-info/DESCRIPTION.rst
bomshell-1.1.0.dist-info/METADATA
bomshell-1.1.0.dist-info/RECORD
bomshell-1.1.0.dist-info/WHEEL
bomshell-1.1.0.dist-info/entry_points.txt
bomshell-1.1.0.dist-info/metadata.json
bomshell-1.1.0.dist-info/top_level.txt
