Metadata-Version: 2.0
Name: bomshell
Version: 1.1.0
Summary: Retrieve weather data from the Australian Bureau of Meteorology
Home-page: https://github.com/sthysel/bomshell
Author: sthysel
Author-email: sthysel@gmail.com
License: GPLv2
Platform: UNKNOWN
Classifier: Development Status :: 5 - Production/Stable
Classifier: Operating System :: Unix
Classifier: Operating System :: POSIX
Classifier: Programming Language :: Python
Classifier: Programming Language :: Python :: 2.7
Classifier: Programming Language :: Python :: 3.6
Classifier: Programming Language :: Python :: Implementation :: CPython
Classifier: Programming Language :: Python :: Implementation :: PyPy
Classifier: Topic :: Utilities
Requires-Dist: click
Requires-Dist: dataset
Requires-Dist: dbfread
Requires-Dist: ftputil
Requires-Dist: pyxdg
Requires-Dist: requests
Requires-Dist: tabulate
